geojsonplot/__init__.py
geojsonplot/geojsonplot.py
geojsonplot-0.0.3.dist-info/LICENSE
geojsonplot-0.0.3.dist-info/METADATA
geojsonplot-0.0.3.dist-info/WHEEL
geojsonplot-0.0.3.dist-info/top_level.txt
geojsonplot-0.0.3.dist-info/RECORD
