Metadata-Version: 2.1
Name: geojsonplot
Version: 0.0.3
Summary: A small, simple geojsonplot package
Author-email: Kyoseung Koo <koo@dbs.snu.ac.kr>
Project-URL: Homepage, https://dbs.snu.ac.kr/
Project-URL: Bug Tracker, https://dbs.snu.ac.kr/
Classifier: Programming Language :: Python :: 3
Classifier: Operating System :: OS Independent
Requires-Python: >=3.8.2
License-File: LICENSE
Requires-Dist: geopandas (>=0.12.2)
Requires-Dist: contextily (>=1.3.0)
Requires-Dist: ipympl (>=0.9.3)
